radia/__init__.py
radia/analytical_magnet.py
radia/cylindrical_magnet.py
radia/esim_cell_problem.py
radia/esim_coupled_solver.py
radia/esim_vtk_export.py
radia/esim_workpiece.py
radia/libiomp5md.dll
radia/mkl_avx2.2.dll
radia/mkl_core.2.dll
radia/mkl_intel_thread.2.dll
radia/mkl_rt.2.dll
radia/mkl_vml_avx2.2.dll
radia/nastran_mesh_import.py
radia/netgen_mesh_import.py
radia/radia.pyd
radia/radia_coil_builder.py
radia/radia_ngsolve.pyd
radia-1.5.0.dist-info/licenses/LICENSE
radia-1.5.0.dist-info/METADATA
radia-1.5.0.dist-info/WHEEL
radia-1.5.0.dist-info/top_level.txt
radia-1.5.0.dist-info/RECORD
