Metadata-Version: 2.4
Name: radia
Version: 1.5.0
Summary: Radia 3D Magnetostatics with NGSolve Integration and OpenMP Parallelization
Home-page: https://github.com/ksugahar/Radia_NGSolve
Author: Pascal Elleaume
Author-email: Oleg Chubar <chubar@bnl.gov>
Maintainer: Radia Development Team
License: BSD-style AND MIT
Project-URL: Homepage, https://github.com/ksugahar/Radia_NGSolve
Project-URL: Documentation, https://github.com/ksugahar/Radia_NGSolve/blob/master/README.md
Project-URL: Repository, https://github.com/ksugahar/Radia_NGSolve
Project-URL: Issues, https://github.com/ksugahar/Radia_NGSolve/issues
Project-URL: Original Radia, https://github.com/ochubar/Radia
Project-URL: ESRF Radia Page, https://www.esrf.fr/Accelerators/Groups/InsertionDevices/Software/Radia
Keywords: magnetostatics,magnetic field,radia,ngsolve,fem,synchrotron
Classifier: Development Status :: 5 - Production/Stable
Classifier: Intended Audience :: Science/Research
Classifier: License :: OSI Approved :: BSD License
Classifier: License :: OSI Approved :: MIT License
Classifier: Programming Language :: Python :: 3.12
Classifier: Programming Language :: C++
Classifier: Topic :: Scientific/Engineering :: Physics
Requires-Python: >=3.12
License-File: LICENSE
Requires-Dist: numpy>=1.20
Provides-Extra: viz
Requires-Dist: pyvista>=0.40; extra == "viz"
Requires-Dist: matplotlib>=3.5; extra == "viz"
Provides-Extra: ngsolve
Requires-Dist: ngsolve==6.2.2405; extra == "ngsolve"
Provides-Extra: test
Requires-Dist: pytest>=7.0; extra == "test"
Requires-Dist: pytest-cov>=4.0; extra == "test"
Provides-Extra: dev
Requires-Dist: pytest>=7.0; extra == "dev"
Requires-Dist: pytest-cov>=4.0; extra == "dev"
Requires-Dist: pyvista>=0.40; extra == "dev"
Requires-Dist: matplotlib>=3.5; extra == "dev"
Dynamic: home-page
Dynamic: license-file
Dynamic: requires-python
